feiying_mcp/__init__.py
feiying_mcp/server.py
feiying_mcp/tools/__init__.py
feiying_mcp/tools/audio_tools.py
feiying_mcp/tools/avatar_tools.py
feiying_mcp/tools/query_tools.py
feiying_mcp/tools/video_tools.py
feiying_mcp/tools/voice_tools.py
feiying_mcp/utils/api_client.py
feiying_mcp/utils/config.py
feiying_mcp/utils/database.py
feiying_mcp/utils/migrations.py
feiying_mcp/utils/models.py
feiying_mcp/utils/task_manager.py
feiying_mcp-0.0.7.dist-info/METADATA
feiying_mcp-0.0.7.dist-info/WHEEL
feiying_mcp-0.0.7.dist-info/entry_points.txt
feiying_mcp-0.0.7.dist-info/top_level.txt
feiying_mcp-0.0.7.dist-info/RECORD
