Metadata-Version: 2.4
Name: feiying-mcp
Version: 0.0.7
Summary: 飞影数字人API服务，提供数字人相关功能
Home-page: https://github.com/fancyboi999/feiying-mcp
Author-email: fancy <fancyboi999@gmail.com>
License-Expression: MIT
Project-URL: Homepage, https://github.com/fancyboi999/feiying-mcp
Project-URL: Bug Tracker, https://github.com/fancyboi999/feiying-mcp/issues
Project-URL: Documentation, https://github.com/fancyboi999/feiying-mcp/docs
Classifier: Programming Language :: Python :: 3
Classifier: Programming Language :: Python :: 3.11
Classifier: Operating System :: OS Independent
Requires-Python: >=3.11
Requires-Dist: fastapi>=0.110.0
Requires-Dist: fastmcp>=1.6.0
Requires-Dist: pydantic>=2.11.3
Requires-Dist: requests>=2.32.3
Requires-Dist: aiosqlite>=0.21.0
Requires-Dist: uvicorn>=0.34.2
Requires-Dist: greenlet>=3.2.3
Requires-Dist: sqlalchemy>=2.0.30
Provides-Extra: dev
Requires-Dist: build>=1.2.2.post1; extra == "dev"
Requires-Dist: setuptools>=45; extra == "dev"
Requires-Dist: twine>=6.1.0; extra == "dev"
Dynamic: home-page
Dynamic: requires-python
